Workbook
Name cfg_PBR_max: Config!$B$8
Name cfg_PBR_floor: Config!$B$9
Name cfg_NetCash_positive: Config!$B$10
Name cfg_Liq_min: Config!$B$11
Name cfg_Liq_cap: Config!$B$12
Name w_PBR: Config!$B$15
Name w_NetCash: Config!$B$16
Name w_Liq: Config!$B$17
Name w_Return: Config!$B$18
Name w_GovAct: Config!$B$19
Name cap_NetCashPct: Config!$B$22
Name cap_DivYield: Config!$B$23
Name cap_BuybackYield: Config!$B$24

Sheet README
A1: JP Long-only Prop Fund — Equity Screening Workbook (Complete v1.0)
A3: Purpose: Repeatable weekly screening (Prime/Standard priority; Growth satellite).
A4: Inputs: Fill blue cells in Fundamentals; record primary URLs in Sources.
A5: Template rows: 200 rows are prebuilt. Copy formulas down if you need more.
A6: Outputs: Report_Top20 uses formulas (no dynamic arrays).
A7: Primary sources only: TDnet/JPX, EDINET/FSA, issuer IR PDFs (direct links).
A8: Generated: 2026-01-26 09:00 JST

Sheet Config
A1: Config (Inputs in blue)
A3: Universe
A4: Primary markets (comma separated) | B4: Prime,Standard
A5: Satellite market | B5: Growth
A7: Core Filters
A8: PBR max (core) | B8: 1
A9: PBR floor (for scoring) | B9: 0.2
A10: Net Cash must be > 0 (1=yes) | B10: 1
A11: Min liquidity (Avg traded value, ¥mm/day) | B11: 50
A12: Liquidity cap for scoring (¥mm/day) | B12: 500
A14: Score Weights (sum=100)
A15: Weight: PBR | B15: 35
A16: Weight: NetCash% | B16: 30
A17: Weight: Liquidity | B17: 10
A18: Weight: Div+Buyback yield | B18: 15
A19: Weight: Gov/Activism | B19: 10
A21: Normalization Caps
A22: NetCash% cap | B22: 0.5
A23: Dividend yield cap | B23: 0.05
A24: Buyback yield cap | B24: 0.05

Sheet Universe
A1: Universe (paste listing here)
A2: Ticker | B2: Name | C2: Market | D2: Market Segment | E2: Sector (33) | F2: Sector (17) | G2: ISIN | H2: Listing Date | I2: Delisting Date | J2: Active (1/0) | K2: Notes

Sheet Fundamentals
A1: Fundamentals (blue=input; cite primary URLs)
A2: Ticker | B2: Name | C2: Market Segment | D2: FY End | E2: Period Type | F2: Latest Filing Date | G2: Market Cap (¥mm) | H2: Book Equity (¥mm) | I2: Cash&Eq (¥mm) | J2: ST Inv (¥mm) | K2: Interest-bearing Debt (¥mm) | L2: Net Income (¥mm) | M2: Shares Out (mm) | N2: Price (¥) | O2: Avg Traded Value 3m (¥mm/day) | P2: Dividend Yield | Q2: Buyback Yield | R2: Capital Policy Update (1/0) | S2: Buyback Announced (1/0) | T2: Activist Signal (0/1) | U2: Notes | V2: Source URL (financials) | W2: Source URL (EDINET) | X2: Source URL (capital policy)
B3: =IFERROR(INDEX(Universe!$B$3:$B$3002, MATCH($A3, Universe!$A$3:$A$3002, 0)),"") | C3: =IFERROR(INDEX(Universe!$D$3:$D$3002, MATCH($A3, Universe!$A$3:$A$3002, 0)),"")
B4: =IFERROR(INDEX(Universe!$B$3:$B$3002, MATCH($A4, Universe!$A$3:$A$3002, 0)),"") | C4: =IFERROR(INDEX(Universe!$D$3:$D$3002, MATCH($A4, Universe!$A$3:$A$3002, 0)),"")
B5: =IFERROR(INDEX(Universe!$B$3:$B$3002, MATCH($A5, Universe!$A$3:$A$3002, 0)),"") | C5: =IFERROR(INDEX(Universe!$D$3:$D$3002, MATCH($A5, Universe!$A$3:$A$3002, 0)),"")
B6: =IFERROR(INDEX(Universe!$B$3:$B$3002, MATCH($A6, Universe!$A$3:$A$3002, 0)),"") | C6: =IFERROR(INDEX(Universe!$D$3:$D$3002, MATCH($A6, Universe!$A$3:$A$3002, 0)),"")
B7: =IFERROR(INDEX(Universe!$B$3:$B$3002, MATCH($A7, Universe!$A$3:$A$3002, 0)),"") | C7: =IFERROR(INDEX(Universe!$D$3:$D$3002, MATCH($A7, Universe!$A$3:$A$3002, 0)),"")
B8: =IFERROR(INDEX(Universe!$B$3:$B$3002, MATCH($A8, Universe!$A$3:$A$3002, 0)),"") | C8: =IFERROR(INDEX(Universe!$D$3:$D$3002, MATCH($A8, Universe!$A$3:$A$3002, 0)),"")
B9: =IFERROR(INDEX(Universe!$B$3:$B$3002, MATCH($A9, Universe!$A$3:$A$3002, 0)),"") | C9: =IFERROR(INDEX(Universe!$D$3:$D$3002, MATCH($A9, Universe!$A$3:$A$3002, 0)),"")
B10: =IFERROR(INDEX(Universe!$B$3:$B$3002, MATCH($A10, Universe!$A$3:$A$3002, 0)),"") | C10: =IFERROR(INDEX(Universe!$D$3:$D$3002, MATCH($A10, Universe!$A$3:$A$3002, 0)),"")
B11: =IFERROR(INDEX(Universe!$B$3:$B$3002, MATCH($A11, Universe!$A$3:$A$3002, 0)),"") | C11: =IFERROR(INDEX(Universe!$D$3:$D$3002, MATCH($A11, Universe!$A$3:$A$3002, 0)),"")
B12: =IFERROR(INDEX(Universe!$B$3:$B$3002, MATCH($A12, Universe!$A$3:$A$3002, 0)),"") | C12: =IFERROR(INDEX(Universe!$D$3:$D$3002, MATCH($A12, Universe!$A$3:$A$3002, 0)),"")
B13: =IFERROR(INDEX(Universe!$B$3:$B$3002, MATCH($A13, Universe!$A$3:$A$3002, 0)),"") | C13: =IFERROR(INDEX(Universe!$D$3:$D$3002, MATCH($A13, Universe!$A$3:$A$3002, 0)),"")
B14: =IFERROR(INDEX(Universe!$B$3:$B$3002, MATCH($A14, Universe!$A$3:$A$3002, 0)),"") | C14: =IFERROR(INDEX(Universe!$D$3:$D$3002, MATCH($A14, Universe!$A$3:$A$3002, 0)),"")
... B202: =IFERROR(INDEX(Universe!$B$3:$B$3002, MATCH($A202, Universe!$A$3:$A$3002, 0)),"") | C202: =IFERROR(INDEX(Universe!$D$3:$D$3002, MATCH($A202, Universe!$A$3:$A$3002, 0)),"")

Sheet Derived
A1: Derived Metrics (formulas)
A2: Ticker | B2: Name | C2: Market Segment | D2: Market Cap (¥mm) | E2: Book Equity (¥mm) | F2: PBR (x) | G2: Net Cash (¥mm) | H2: Net Cash / MktCap | I2: ROE | J2: Avg Traded Value 3m (¥mm/day) | K2: Core Pass (1/0) | L2: Core Fail Reason | M2: Data Missing Flag | N2: Notes
A3: =Fundamentals!A3 | B3: =Fundamentals!B3 | C3: =Fundamentals!C3 | D3: =Fundamentals!G3 | E3: =Fundamentals!H3 | F3: =IF(OR($D3="",$E3="",$E3=0),"",$D3/$E3) | G3: =IF(OR(Fundamentals!I3="",Fundamentals!J3="",Fundamentals!K3=""),"",Fundamentals!I3+Fundamentals!J3-Fundamentals!K3) | H3: =IF(OR($G3="",$D3="",$D3=0),"",$G3/$D3) | I3: =IF(OR(Fundamentals!L3="",$E3="",$E3=0),"",Fundamentals!L3/$E3) | J3: =Fundamentals!O3 | K3: =IF(OR($A3=""),"",IF(AND($C3<>"Growth",$F3<>"",$F3<cfg_PBR_max,$G3<>"",$G3>0,$J3<>"",$J3>=cfg_Liq_min),1,0)) | L3: =IF($K3="","",IF($K3=1,"",(IF($C3="Growth","Market=Growth; ",""))&(IF(OR($F3="",$F3>=cfg_PBR_max),"PBR>=max/missing; ",""))&(IF(OR($G3="",$G3<=0),"NetCash<=0/missing; ",""))&(IF(OR($J3="",$J3<cfg_Liq_min),"Liquidity<min/missing; ","")))) | M3: =IF($A3="","",IF(OR($D3="",$E3="",Fundamentals!I3="",Fundamentals!K3="",$J3=""),1,0)) | N3: =Fundamentals!U3
A4: =Fundamentals!A4 | B4: =Fundamentals!B4 | C4: =Fundamentals!C4 | D4: =Fundamentals!G4 | E4: =Fundamentals!H4 | F4: =IF(OR($D4="",$E4="",$E4=0),"",$D4/$E4) | G4: =IF(OR(Fundamentals!I4="",Fundamentals!J4="",Fundamentals!K4=""),"",Fundamentals!I4+Fundamentals!J4-Fundamentals!K4) | H4: =IF(OR($G4="",$D4="",$D4=0),"",$G4/$D4) | I4: =IF(OR(Fundamentals!L4="",$E4="",$E4=0),"",Fundamentals!L4/$E4) | J4: =Fundamentals!O4 | K4: =IF(OR($A4=""),"",IF(AND($C4<>"Growth",$F4<>"",$F4<cfg_PBR_max,$G4<>"",$G4>0,$J4<>"",$J4>=cfg_Liq_min),1,0)) | L4: =IF($K4="","",IF($K4=1,"",(IF($C4="Growth","Market=Growth; ",""))&(IF(OR($F4="",$F4>=cfg_PBR_max),"PBR>=max/missing; ",""))&(IF(OR($G4="",$G4<=0),"NetCash<=0/missing; ",""))&(IF(OR($J4="",$J4<cfg_Liq_min),"Liquidity<min/missing; ","")))) | M4: =IF($A4="","",IF(OR($D4="",$E4="",Fundamentals!I4="",Fundamentals!K4="",$J4=""),1,0)) | N4: =Fundamentals!U4
A5: =Fundamentals!A5 | B5: =Fundamentals!B5 | C5: =Fundamentals!C5 | D5: =Fundamentals!G5 | E5: =Fundamentals!H5 | F5: =IF(OR($D5="",$E5="",$E5=0),"",$D5/$E5) | G5: =IF(OR(Fundamentals!I5="",Fundamentals!J5="",Fundamentals!K5=""),"",Fundamentals!I5+Fundamentals!J5-Fundamentals!K5) | H5: =IF(OR($G5="",$D5="",$D5=0),"",$G5/$D5) | I5: =IF(OR(Fundamentals!L5="",$E5="",$E5=0),"",Fundamentals!L5/$E5) | J5: =Fundamentals!O5 | K5: =IF(OR($A5=""),"",IF(AND($C5<>"Growth",$F5<>"",$F5<cfg_PBR_max,$G5<>"",$G5>0,$J5<>"",$J5>=cfg_Liq_min),1,0)) | L5: =IF($K5="","",IF($K5=1,"",(IF($C5="Growth","Market=Growth; ",""))&(IF(OR($F5="",$F5>=cfg_PBR_max),"PBR>=max/missing; ",""))&(IF(OR($G5="",$G5<=0),"NetCash<=0/missing; ",""))&(IF(OR($J5="",$J5<cfg_Liq_min),"Liquidity<min/missing; ","")))) | M5: =IF($A5="","",IF(OR($D5="",$E5="",Fundamentals!I5="",Fundamentals!K5="",$J5=""),1,0)) | N5: =Fundamentals!U5
A6: =Fundamentals!A6 | B6: =Fundamentals!B6 | C6: =Fundamentals!C6 | D6: =Fundamentals!G6 | E6: =Fundamentals!H6 | F6: =IF(OR($D6="",$E6="",$E6=0),"",$D6/$E6) | G6: =IF(OR(Fundamentals!I6="",Fundamentals!J6="",Fundamentals!K6=""),"",Fundamentals!I6+Fundamentals!J6-Fundamentals!K6) | H6: =IF(OR($G6="",$D6="",$D6=0),"",$G6/$D6) | I6: =IF(OR(Fundamentals!L6="",$E6="",$E6=0),"",Fundamentals!L6/$E6) | J6: =Fundamentals!O6 | K6: =IF(OR($A6=""),"",IF(AND($C6<>"Growth",$F6<>"",$F6<cfg_PBR_max,$G6<>"",$G6>0,$J6<>"",$J6>=cfg_Liq_min),1,0)) | L6: =IF($K6="","",IF($K6=1,"",(IF($C6="Growth","Market=Growth; ",""))&(IF(OR($F6="",$F6>=cfg_PBR_max),"PBR>=max/missing; ",""))&(IF(OR($G6="",$G6<=0),"NetCash<=0/missing; ",""))&(IF(OR($J6="",$J6<cfg_Liq_min),"Liquidity<min/missing; ","")))) | M6: =IF($A6="","",IF(OR($D6="",$E6="",Fundamentals!I6="",Fundamentals!K6="",$J6=""),1,0)) | N6: =Fundamentals!U6
A7: =Fundamentals!A7 | B7: =Fundamentals!B7 | C7: =Fundamentals!C7 | D7: =Fundamentals!G7 | E7: =Fundamentals!H7 | F7: =IF(OR($D7="",$E7="",$E7=0),"",$D7/$E7) | G7: =IF(OR(Fundamentals!I7="",Fundamentals!J7="",Fundamentals!K7=""),"",Fundamentals!I7+Fundamentals!J7-Fundamentals!K7) | H7: =IF(OR($G7="",$D7="",$D7=0),"",$G7/$D7) | I7: =IF(OR(Fundamentals!L7="",$E7="",$E7=0),"",Fundamentals!L7/$E7) | J7: =Fundamentals!O7 | K7: =IF(OR($A7=""),"",IF(AND($C7<>"Growth",$F7<>"",$F7<cfg_PBR_max,$G7<>"",$G7>0,$J7<>"",$J7>=cfg_Liq_min),1,0)) | L7: =IF($K7="","",IF($K7=1,"",(IF($C7="Growth","Market=Growth; ",""))&(IF(OR($F7="",$F7>=cfg_PBR_max),"PBR>=max/missing; ",""))&(IF(OR($G7="",$G7<=0),"NetCash<=0/missing; ",""))&(IF(OR($J7="",$J7<cfg_Liq_min),"Liquidity<min/missing; ","")))) | M7: =IF($A7="","",IF(OR($D7="",$E7="",Fundamentals!I7="",Fundamentals!K7="",$J7=""),1,0)) | N7: =Fundamentals!U7
A8: =Fundamentals!A8 | B8: =Fundamentals!B8 | C8: =Fundamentals!C8 | D8: =Fundamentals!G8 | E8: =Fundamentals!H8 | F8: =IF(OR($D8="",$E8="",$E8=0),"",$D8/$E8) | G8: =IF(OR(Fundamentals!I8="",Fundamentals!J8="",Fundamentals!K8=""),"",Fundamentals!I8+Fundamentals!J8-Fundamentals!K8) | H8: =IF(OR($G8="",$D8="",$D8=0),"",$G8/$D8) | I8: =IF(OR(Fundamentals!L8="",$E8="",$E8=0),"",Fundamentals!L8/$E8) | J8: =Fundamentals!O8 | K8: =IF(OR($A8=""),"",IF(AND($C8<>"Growth",$F8<>"",$F8<cfg_PBR_max,$G8<>"",$G8>0,$J8<>"",$J8>=cfg_Liq_min),1,0)) | L8: =IF($K8="","",IF($K8=1,"",(IF($C8="Growth","Market=Growth; ",""))&(IF(OR($F8="",$F8>=cfg_PBR_max),"PBR>=max/missing; ",""))&(IF(OR($G8="",$G8<=0),"NetCash<=0/missing; ",""))&(IF(OR($J8="",$J8<cfg_Liq_min),"Liquidity<min/missing; ","")))) | M8: =IF($A8="","",IF(OR($D8="",$E8="",Fundamentals!I8="",Fundamentals!K8="",$J8=""),1,0)) | N8: =Fundamentals!U8
A9: =Fundamentals!A9 | B9: =Fundamentals!B9 | C9: =Fundamentals!C9 | D9: =Fundamentals!G9 | E9: =Fundamentals!H9 | F9: =IF(OR($D9="",$E9="",$E9=0),"",$D9/$E9) | G9: =IF(OR(Fundamentals!I9="",Fundamentals!J9="",Fundamentals!K9=""),"",Fundamentals!I9+Fundamentals!J9-Fundamentals!K9) | H9: =IF(OR($G9="",$D9="",$D9=0),"",$G9/$D9) | I9: =IF(OR(Fundamentals!L9="",$E9="",$E9=0),"",Fundamentals!L9/$E9) | J9: =Fundamentals!O9 | K9: =IF(OR($A9=""),"",IF(AND($C9<>"Growth",$F9<>"",$F9<cfg_PBR_max,$G9<>"",$G9>0,$J9<>"",$J9>=cfg_Liq_min),1,0)) | L9: =IF($K9="","",IF($K9=1,"",(IF($C9="Growth","Market=Growth; ",""))&(IF(OR($F9="",$F9>=cfg_PBR_max),"PBR>=max/missing; ",""))&(IF(OR($G9="",$G9<=0),"NetCash<=0/missing; ",""))&(IF(OR($J9="",$J9<cfg_Liq_min),"Liquidity<min/missing; ","")))) | M9: =IF($A9="","",IF(OR($D9="",$E9="",Fundamentals!I9="",Fundamentals!K9="",$J9=""),1,0)) | N9: =Fundamentals!U9
A10: =Fundamentals!A10 | B10: =Fundamentals!B10 | C10: =Fundamentals!C10 | D10: =Fundamentals!G10 | E10: =Fundamentals!H10 | F10: =IF(OR($D10="",$E10="",$E10=0),"",$D10/$E10) | G10: =IF(OR(Fundamentals!I10="",Fundamentals!J10="",Fundamentals!K10=""),"",Fundamentals!I10+Fundamentals!J10-Fundamentals!K10) | H10: =IF(OR($G10="",$D10="",$D10=0),"",$G10/$D10) | I10: =IF(OR(Fundamentals!L10="",$E10="",$E10=0),"",Fundamentals!L10/$E10) | J10: =Fundamentals!O10 | K10: =IF(OR($A10=""),"",IF(AND($C10<>"Growth",$F10<>"",$F10<cfg_PBR_max,$G10<>"",$G10>0,$J10<>"",$J10>=cfg_Liq_min),1,0)) | L10: =IF($K10="","",IF($K10=1,"",(IF($C10="Growth","Market=Growth; ",""))&(IF(OR($F10="",$F10>=cfg_PBR_max),"PBR>=max/missing; ",""))&(IF(OR($G10="",$G10<=0),"NetCash<=0/missing; ",""))&(IF(OR($J10="",$J10<cfg_Liq_min),"Liquidity<min/missing; ","")))) | M10: =IF($A10="","",IF(OR($D10="",$E10="",Fundamentals!I10="",Fundamentals!K10="",$J10=""),1,0)) | N10: =Fundamentals!U10
A11: =Fundamentals!A11 | B11: =Fundamentals!B11 | C11: =Fundamentals!C11 | D11: =Fundamentals!G11 | E11: =Fundamentals!H11 | F11: =IF(OR($D11="",$E11="",$E11=0),"",$D11/$E11) | G11: =IF(OR(Fundamentals!I11="",Fundamentals!J11="",Fundamentals!K11=""),"",Fundamentals!I11+Fundamentals!J11-Fundamentals!K11) | H11: =IF(OR($G11="",$D11="",$D11=0),"",$G11/$D11) | I11: =IF(OR(Fundamentals!L11="",$E11="",$E11=0),"",Fundamentals!L11/$E11) | J11: =Fundamentals!O11 | K11: =IF(OR($A11=""),"",IF(AND($C11<>"Growth",$F11<>"",$F11<cfg_PBR_max,$G11<>"",$G11>0,$J11<>"",$J11>=cfg_Liq_min),1,0)) | L11: =IF($K11="","",IF($K11=1,"",(IF($C11="Growth","Market=Growth; ",""))&(IF(OR($F11="",$F11>=cfg_PBR_max),"PBR>=max/missing; ",""))&(IF(OR($G11="",$G11<=0),"NetCash<=0/missing; ",""))&(IF(OR($J11="",$J11<cfg_Liq_min),"Liquidity<min/missing; ","")))) | M11: =IF($A11="","",IF(OR($D11="",$E11="",Fundamentals!I11="",Fundamentals!K11="",$J11=""),1,0)) | N11: =Fundamentals!U11
A12: =Fundamentals!A12 | B12: =Fundamentals!B12 | C12: =Fundamentals!C12 | D12: =Fundamentals!G12 | E12: =Fundamentals!H12 | F12: =IF(OR($D12="",$E12="",$E12=0),"",$D12/$E12) | G12: =IF(OR(Fundamentals!I12="",Fundamentals!J12="",Fundamentals!K12=""),"",Fundamentals!I12+Fundamentals!J12-Fundamentals!K12) | H12: =IF(OR($G12="",$D12="",$D12=0),"",$G12/$D12) | I12: =IF(OR(Fundamentals!L12="",$E12="",$E12=0),"",Fundamentals!L12/$E12) | J12: =Fundamentals!O12 | K12: =IF(OR($A12=""),"",IF(AND($C12<>"Growth",$F12<>"",$F12<cfg_PBR_max,$G12<>"",$G12>0,$J12<>"",$J12>=cfg_Liq_min),1,0)) | L12: =IF($K12="","",IF($K12=1,"",(IF($C12="Growth","Market=Growth; ",""))&(IF(OR($F12="",$F12>=cfg_PBR_max),"PBR>=max/missing; ",""))&(IF(OR($G12="",$G12<=0),"NetCash<=0/missing; ",""))&(IF(OR($J12="",$J12<cfg_Liq_min),"Liquidity<min/missing; ","")))) | M12: =IF($A12="","",IF(OR($D12="",$E12="",Fundamentals!I12="",Fundamentals!K12="",$J12=""),1,0)) | N12: =Fundamentals!U12
A13: =Fundamentals!A13 | B13: =Fundamentals!B13 | C13: =Fundamentals!C13 | D13: =Fundamentals!G13 | E13: =Fundamentals!H13 | F13: =IF(OR($D13="",$E13="",$E13=0),"",$D13/$E13) | G13: =IF(OR(Fundamentals!I13="",Fundamentals!J13="",Fundamentals!K13=""),"",Fundamentals!I13+Fundamentals!J13-Fundamentals!K13) | H13: =IF(OR($G13="",$D13="",$D13=0),"",$G13/$D13) | I13: =IF(OR(Fundamentals!L13="",$E13="",$E13=0),"",Fundamentals!L13/$E13) | J13: =Fundamentals!O13 | K13: =IF(OR($A13=""),"",IF(AND($C13<>"Growth",$F13<>"",$F13<cfg_PBR_max,$G13<>"",$G13>0,$J13<>"",$J13>=cfg_Liq_min),1,0)) | L13: =IF($K13="","",IF($K13=1,"",(IF($C13="Growth","Market=Growth; ",""))&(IF(OR($F13="",$F13>=cfg_PBR_max),"PBR>=max/missing; ",""))&(IF(OR($G13="",$G13<=0),"NetCash<=0/missing; ",""))&(IF(OR($J13="",$J13<cfg_Liq_min),"Liquidity<min/missing; ","")))) | M13: =IF($A13="","",IF(OR($D13="",$E13="",Fundamentals!I13="",Fundamentals!K13="",$J13=""),1,0)) | N13: =Fundamentals!U13
A14: =Fundamentals!A14 | B14: =Fundamentals!B14 | C14: =Fundamentals!C14 | D14: =Fundamentals!G14 | E14: =Fundamentals!H14 | F14: =IF(OR($D14="",$E14="",$E14=0),"",$D14/$E14) | G14: =IF(OR(Fundamentals!I14="",Fundamentals!J14="",Fundamentals!K14=""),"",Fundamentals!I14+Fundamentals!J14-Fundamentals!K14) | H14: =IF(OR($G14="",$D14="",$D14=0),"",$G14/$D14) | I14: =IF(OR(Fundamentals!L14="",$E14="",$E14=0),"",Fundamentals!L14/$E14) | J14: =Fundamentals!O14 | K14: =IF(OR($A14=""),"",IF(AND($C14<>"Growth",$F14<>"",$F14<cfg_PBR_max,$G14<>"",$G14>0,$J14<>"",$J14>=cfg_Liq_min),1,0)) | L14: =IF($K14="","",IF($K14=1,"",(IF($C14="Growth","Market=Growth; ",""))&(IF(OR($F14="",$F14>=cfg_PBR_max),"PBR>=max/missing; ",""))&(IF(OR($G14="",$G14<=0),"NetCash<=0/missing; ",""))&(IF(OR($J14="",$J14<cfg_Liq_min),"Liquidity<min/missing; ","")))) | M14: =IF($A14="","",IF(OR($D14="",$E14="",Fundamentals!I14="",Fundamentals!K14="",$J14=""),1,0)) | N14: =Fundamentals!U14
... A202: =Fundamentals!A202 | B202: =Fundamentals!B202 | C202: =Fundamentals!C202 | D202: =Fundamentals!G202 | E202: =Fundamentals!H202 | F202: =IF(OR($D202="",$E202="",$E202=0),"",$D202/$E202) | G202: =IF(OR(Fundamentals!I202="",Fundamentals!J202="",Fundamentals!K202=""),"",Fundamentals!I202+Fundamentals!J202-Fundamentals!K202) | H202: =IF(OR($G202="",$D202="",$D202=0),"",$G202/$D202) | I202: =IF(OR(Fundamentals!L202="",$E202="",$E202=0),"",Fundamentals!L202/$E202) | J202: =Fundamentals!O202 | K202: =IF(OR($A202=""),"",IF(AND($C202<>"Growth",$F202<>"",$F202<cfg_PBR_max,$G202<>"",$G202>0,$J202<>"",$J202>=cfg_Liq_min),1,0)) | L202: =IF($K202="","",IF($K202=1,"",(IF($C202="Growth","Market=Growth; ",""))&(IF(OR($F202="",$F202>=cfg_PBR_max),"PBR>=max/missing; ",""))&(IF(OR($G202="",$G202<=0),"NetCash<=0/missing; ",""))&(IF(OR($J202="",$J202<cfg_Liq_min),"Liquidity<min/missing; ","")))) | M202: =IF($A202="","",IF(OR($D202="",$E202="",Fundamentals!I202="",Fundamentals!K202="",$J202=""),1,0)) | N202: =Fundamentals!U202

Sheet Scores
A1: Scores (TotalScore 0-100; core-pass only for Top20)
A2: Ticker | B2: Name | C2: Market Segment | D2: Core Pass (1/0) | E2: PBR | F2: PBR Score (0-1) | G2: NetCash% | H2: NetCash Score (0-1) | I2: Liquidity (¥mm/day) | J2: Liquidity Score (0-1) | K2: Div Yield | L2: Buyback Yield | M2: Return Score (0-1) | N2: Gov/Act Inputs (0-1) | O2: Gov/Act Score (0-1) | P2: Total Score (0-100) | Q2: ScoreKey | R2: Rank (1=best) | S2: Exclude Reason | T2: CoreScoreKey
A3: =Derived!A3 | B3: =Derived!B3 | C3: =Derived!C3 | D3: =Derived!K3 | E3: =Derived!F3 | F3: =IF(OR($E3=""),"",MAX(0,MIN(1,(cfg_PBR_max-MIN($E3,cfg_PBR_max))/(cfg_PBR_max-cfg_PBR_floor)))) | G3: =Derived!H3 | H3: =IF(OR($G3=""),"",MAX(0,MIN(1,MIN($G3,cap_NetCashPct)/cap_NetCashPct))) | I3: =Derived!J3 | J3: =IF(OR($I3=""),"",MAX(0,MIN(1,($I3-cfg_Liq_min)/(cfg_Liq_cap-cfg_Liq_min)))) | K3: =Fundamentals!P3 | L3: =Fundamentals!Q3 | M3: =IF(AND($K3="",$L3=""),"",MIN(1,IF($K3="",0,MIN($K3,cap_DivYield)/cap_DivYield)*0.5+IF($L3="",0,MIN($L3,cap_BuybackYield)/cap_BuybackYield)*0.5)) | N3: =IF($A3="","",AVERAGE(IF(Fundamentals!R3="",0,Fundamentals!R3),IF(Fundamentals!S3="",0,Fundamentals!S3),IF(Fundamentals!T3="",0,Fundamentals!T3))) | O3: =IF($A3="","",MAX(0,MIN(1,$N3))) | P3: =IF($A3="","",ROUND(w_PBR*$F3+w_NetCash*$H3+w_Liq*$J3+w_Return*$M3+w_GovAct*$O3,2)) | Q3: =IF($A3="","",$P3+(100000-ROW())/100000000) | R3: =IF($A3="","",IF($D3<>1,"",RANK.EQ($Q3,$Q$3:$Q$202,0))) | S3: =IF($A3="","",IF($D3=1,"",Derived!L3)) | T3: =IF($D3=1,$Q3,"")
A4: =Derived!A4 | B4: =Derived!B4 | C4: =Derived!C4 | D4: =Derived!K4 | E4: =Derived!F4 | F4: =IF(OR($E4=""),"",MAX(0,MIN(1,(cfg_PBR_max-MIN($E4,cfg_PBR_max))/(cfg_PBR_max-cfg_PBR_floor)))) | G4: =Derived!H4 | H4: =IF(OR($G4=""),"",MAX(0,MIN(1,MIN($G4,cap_NetCashPct)/cap_NetCashPct))) | I4: =Derived!J4 | J4: =IF(OR($I4=""),"",MAX(0,MIN(1,($I4-cfg_Liq_min)/(cfg_Liq_cap-cfg_Liq_min)))) | K4: =Fundamentals!P4 | L4: =Fundamentals!Q4 | M4: =IF(AND($K4="",$L4=""),"",MIN(1,IF($K4="",0,MIN($K4,cap_DivYield)/cap_DivYield)*0.5+IF($L4="",0,MIN($L4,cap_BuybackYield)/cap_BuybackYield)*0.5)) | N4: =IF($A4="","",AVERAGE(IF(Fundamentals!R4="",0,Fundamentals!R4),IF(Fundamentals!S4="",0,Fundamentals!S4),IF(Fundamentals!T4="",0,Fundamentals!T4))) | O4: =IF($A4="","",MAX(0,MIN(1,$N4))) | P4: =IF($A4="","",ROUND(w_PBR*$F4+w_NetCash*$H4+w_Liq*$J4+w_Return*$M4+w_GovAct*$O4,2)) | Q4: =IF($A4="","",$P4+(100000-ROW())/100000000) | R4: =IF($A4="","",IF($D4<>1,"",RANK.EQ($Q4,$Q$3:$Q$202,0))) | S4: =IF($A4="","",IF($D4=1,"",Derived!L4)) | T4: =IF($D4=1,$Q4,"")
A5: =Derived!A5 | B5: =Derived!B5 | C5: =Derived!C5 | D5: =Derived!K5 | E5: =Derived!F5 | F5: =IF(OR($E5=""),"",MAX(0,MIN(1,(cfg_PBR_max-MIN($E5,cfg_PBR_max))/(cfg_PBR_max-cfg_PBR_floor)))) | G5: =Derived!H5 | H5: =IF(OR($G5=""),"",MAX(0,MIN(1,MIN($G5,cap_NetCashPct)/cap_NetCashPct))) | I5: =Derived!J5 | J5: =IF(OR($I5=""),"",MAX(0,MIN(1,($I5-cfg_Liq_min)/(cfg_Liq_cap-cfg_Liq_min)))) | K5: =Fundamentals!P5 | L5: =Fundamentals!Q5 | M5: =IF(AND($K5="",$L5=""),"",MIN(1,IF($K5="",0,MIN($K5,cap_DivYield)/cap_DivYield)*0.5+IF($L5="",0,MIN($L5,cap_BuybackYield)/cap_BuybackYield)*0.5)) | N5: =IF($A5="","",AVERAGE(IF(Fundamentals!R5="",0,Fundamentals!R5),IF(Fundamentals!S5="",0,Fundamentals!S5),IF(Fundamentals!T5="",0,Fundamentals!T5))) | O5: =IF($A5="","",MAX(0,MIN(1,$N5))) | P5: =IF($A5="","",ROUND(w_PBR*$F5+w_NetCash*$H5+w_Liq*$J5+w_Return*$M5+w_GovAct*$O5,2)) | Q5: =IF($A5="","",$P5+(100000-ROW())/100000000) | R5: =IF($A5="","",IF($D5<>1,"",RANK.EQ($Q5,$Q$3:$Q$202,0))) | S5: =IF($A5="","",IF($D5=1,"",Derived!L5)) | T5: =IF($D5=1,$Q5,"")
A6: =Derived!A6 | B6: =Derived!B6 | C6: =Derived!C6 | D6: =Derived!K6 | E6: =Derived!F6 | F6: =IF(OR($E6=""),"",MAX(0,MIN(1,(cfg_PBR_max-MIN($E6,cfg_PBR_max))/(cfg_PBR_max-cfg_PBR_floor)))) | G6: =Derived!H6 | H6: =IF(OR($G6=""),"",MAX(0,MIN(1,MIN($G6,cap_NetCashPct)/cap_NetCashPct))) | I6: =Derived!J6 | J6: =IF(OR($I6=""),"",MAX(0,MIN(1,($I6-cfg_Liq_min)/(cfg_Liq_cap-cfg_Liq_min)))) | K6: =Fundamentals!P6 | L6: =Fundamentals!Q6 | M6: =IF(AND($K6="",$L6=""),"",MIN(1,IF($K6="",0,MIN($K6,cap_DivYield)/cap_DivYield)*0.5+IF($L6="",0,MIN($L6,cap_BuybackYield)/cap_BuybackYield)*0.5)) | N6: =IF($A6="","",AVERAGE(IF(Fundamentals!R6="",0,Fundamentals!R6),IF(Fundamentals!S6="",0,Fundamentals!S6),IF(Fundamentals!T6="",0,Fundamentals!T6))) | O6: =IF($A6="","",MAX(0,MIN(1,$N6))) | P6: =IF($A6="","",ROUND(w_PBR*$F6+w_NetCash*$H6+w_Liq*$J6+w_Return*$M6+w_GovAct*$O6,2)) | Q6: =IF($A6="","",$P6+(100000-ROW())/100000000) | R6: =IF($A6="","",IF($D6<>1,"",RANK.EQ($Q6,$Q$3:$Q$202,0))) | S6: =IF($A6="","",IF($D6=1,"",Derived!L6)) | T6: =IF($D6=1,$Q6,"")
A7: =Derived!A7 | B7: =Derived!B7 | C7: =Derived!C7 | D7: =Derived!K7 | E7: =Derived!F7 | F7: =IF(OR($E7=""),"",MAX(0,MIN(1,(cfg_PBR_max-MIN($E7,cfg_PBR_max))/(cfg_PBR_max-cfg_PBR_floor)))) | G7: =Derived!H7 | H7: =IF(OR($G7=""),"",MAX(0,MIN(1,MIN($G7,cap_NetCashPct)/cap_NetCashPct))) | I7: =Derived!J7 | J7: =IF(OR($I7=""),"",MAX(0,MIN(1,($I7-cfg_Liq_min)/(cfg_Liq_cap-cfg_Liq_min)))) | K7: =Fundamentals!P7 | L7: =Fundamentals!Q7 | M7: =IF(AND($K7="",$L7=""),"",MIN(1,IF($K7="",0,MIN($K7,cap_DivYield)/cap_DivYield)*0.5+IF($L7="",0,MIN($L7,cap_BuybackYield)/cap_BuybackYield)*0.5)) | N7: =IF($A7="","",AVERAGE(IF(Fundamentals!R7="",0,Fundamentals!R7),IF(Fundamentals!S7="",0,Fundamentals!S7),IF(Fundamentals!T7="",0,Fundamentals!T7))) | O7: =IF($A7="","",MAX(0,MIN(1,$N7))) | P7: =IF($A7="","",ROUND(w_PBR*$F7+w_NetCash*$H7+w_Liq*$J7+w_Return*$M7+w_GovAct*$O7,2)) | Q7: =IF($A7="","",$P7+(100000-ROW())/100000000) | R7: =IF($A7="","",IF($D7<>1,"",RANK.EQ($Q7,$Q$3:$Q$202,0))) | S7: =IF($A7="","",IF($D7=1,"",Derived!L7)) | T7: =IF($D7=1,$Q7,"")
A8: =Derived!A8 | B8: =Derived!B8 | C8: =Derived!C8 | D8: =Derived!K8 | E8: =Derived!F8 | F8: =IF(OR($E8=""),"",MAX(0,MIN(1,(cfg_PBR_max-MIN($E8,cfg_PBR_max))/(cfg_PBR_max-cfg_PBR_floor)))) | G8: =Derived!H8 | H8: =IF(OR($G8=""),"",MAX(0,MIN(1,MIN($G8,cap_NetCashPct)/cap_NetCashPct))) | I8: =Derived!J8 | J8: =IF(OR($I8=""),"",MAX(0,MIN(1,($I8-cfg_Liq_min)/(cfg_Liq_cap-cfg_Liq_min)))) | K8: =Fundamentals!P8 | L8: =Fundamentals!Q8 | M8: =IF(AND($K8="",$L8=""),"",MIN(1,IF($K8="",0,MIN($K8,cap_DivYield)/cap_DivYield)*0.5+IF($L8="",0,MIN($L8,cap_BuybackYield)/cap_BuybackYield)*0.5)) | N8: =IF($A8="","",AVERAGE(IF(Fundamentals!R8="",0,Fundamentals!R8),IF(Fundamentals!S8="",0,Fundamentals!S8),IF(Fundamentals!T8="",0,Fundamentals!T8))) | O8: =IF($A8="","",MAX(0,MIN(1,$N8))) | P8: =IF($A8="","",ROUND(w_PBR*$F8+w_NetCash*$H8+w_Liq*$J8+w_Return*$M8+w_GovAct*$O8,2)) | Q8: =IF($A8="","",$P8+(100000-ROW())/100000000) | R8: =IF($A8="","",IF($D8<>1,"",RANK.EQ($Q8,$Q$3:$Q$202,0))) | S8: =IF($A8="","",IF($D8=1,"",Derived!L8)) | T8: =IF($D8=1,$Q8,"")
A9: =Derived!A9 | B9: =Derived!B9 | C9: =Derived!C9 | D9: =Derived!K9 | E9: =Derived!F9 | F9: =IF(OR($E9=""),"",MAX(0,MIN(1,(cfg_PBR_max-MIN($E9,cfg_PBR_max))/(cfg_PBR_max-cfg_PBR_floor)))) | G9: =Derived!H9 | H9: =IF(OR($G9=""),"",MAX(0,MIN(1,MIN($G9,cap_NetCashPct)/cap_NetCashPct))) | I9: =Derived!J9 | J9: =IF(OR($I9=""),"",MAX(0,MIN(1,($I9-cfg_Liq_min)/(cfg_Liq_cap-cfg_Liq_min)))) | K9: =Fundamentals!P9 | L9: =Fundamentals!Q9 | M9: =IF(AND($K9="",$L9=""),"",MIN(1,IF($K9="",0,MIN($K9,cap_DivYield)/cap_DivYield)*0.5+IF($L9="",0,MIN($L9,cap_BuybackYield)/cap_BuybackYield)*0.5)) | N9: =IF($A9="","",AVERAGE(IF(Fundamentals!R9="",0,Fundamentals!R9),IF(Fundamentals!S9="",0,Fundamentals!S9),IF(Fundamentals!T9="",0,Fundamentals!T9))) | O9: =IF($A9="","",MAX(0,MIN(1,$N9))) | P9: =IF($A9="","",ROUND(w_PBR*$F9+w_NetCash*$H9+w_Liq*$J9+w_Return*$M9+w_GovAct*$O9,2)) | Q9: =IF($A9="","",$P9+(100000-ROW())/100000000) | R9: =IF($A9="","",IF($D9<>1,"",RANK.EQ($Q9,$Q$3:$Q$202,0))) | S9: =IF($A9="","",IF($D9=1,"",Derived!L9)) | T9: =IF($D9=1,$Q9,"")
A10: =Derived!A10 | B10: =Derived!B10 | C10: =Derived!C10 | D10: =Derived!K10 | E10: =Derived!F10 | F10: =IF(OR($E10=""),"",MAX(0,MIN(1,(cfg_PBR_max-MIN($E10,cfg_PBR_max))/(cfg_PBR_max-cfg_PBR_floor)))) | G10: =Derived!H10 | H10: =IF(OR($G10=""),"",MAX(0,MIN(1,MIN($G10,cap_NetCashPct)/cap_NetCashPct))) | I10: =Derived!J10 | J10: =IF(OR($I10=""),"",MAX(0,MIN(1,($I10-cfg_Liq_min)/(cfg_Liq_cap-cfg_Liq_min)))) | K10: =Fundamentals!P10 | L10: =Fundamentals!Q10 | M10: =IF(AND($K10="",$L10=""),"",MIN(1,IF($K10="",0,MIN($K10,cap_DivYield)/cap_DivYield)*0.5+IF($L10="",0,MIN($L10,cap_BuybackYield)/cap_BuybackYield)*0.5)) | N10: =IF($A10="","",AVERAGE(IF(Fundamentals!R10="",0,Fundamentals!R10),IF(Fundamentals!S10="",0,Fundamentals!S10),IF(Fundamentals!T10="",0,Fundamentals!T10))) | O10: =IF($A10="","",MAX(0,MIN(1,$N10))) | P10: =IF($A10="","",ROUND(w_PBR*$F10+w_NetCash*$H10+w_Liq*$J10+w_Return*$M10+w_GovAct*$O10,2)) | Q10: =IF($A10="","",$P10+(100000-ROW())/100000000) | R10: =IF($A10="","",IF($D10<>1,"",RANK.EQ($Q10,$Q$3:$Q$202,0))) | S10: =IF($A10="","",IF($D10=1,"",Derived!L10)) | T10: =IF($D10=1,$Q10,"")
A11: =Derived!A11 | B11: =Derived!B11 | C11: =Derived!C11 | D11: =Derived!K11 | E11: =Derived!F11 | F11: =IF(OR($E11=""),"",MAX(0,MIN(1,(cfg_PBR_max-MIN($E11,cfg_PBR_max))/(cfg_PBR_max-cfg_PBR_floor)))) | G11: =Derived!H11 | H11: =IF(OR($G11=""),"",MAX(0,MIN(1,MIN($G11,cap_NetCashPct)/cap_NetCashPct))) | I11: =Derived!J11 | J11: =IF(OR($I11=""),"",MAX(0,MIN(1,($I11-cfg_Liq_min)/(cfg_Liq_cap-cfg_Liq_min)))) | K11: =Fundamentals!P11 | L11: =Fundamentals!Q11 | M11: =IF(AND($K11="",$L11=""),"",MIN(1,IF($K11="",0,MIN($K11,cap_DivYield)/cap_DivYield)*0.5+IF($L11="",0,MIN($L11,cap_BuybackYield)/cap_BuybackYield)*0.5)) | N11: =IF($A11="","",AVERAGE(IF(Fundamentals!R11="",0,Fundamentals!R11),IF(Fundamentals!S11="",0,Fundamentals!S11),IF(Fundamentals!T11="",0,Fundamentals!T11))) | O11: =IF($A11="","",MAX(0,MIN(1,$N11))) | P11: =IF($A11="","",ROUND(w_PBR*$F11+w_NetCash*$H11+w_Liq*$J11+w_Return*$M11+w_GovAct*$O11,2)) | Q11: =IF($A11="","",$P11+(100000-ROW())/100000000) | R11: =IF($A11="","",IF($D11<>1,"",RANK.EQ($Q11,$Q$3:$Q$202,0))) | S11: =IF($A11="","",IF($D11=1,"",Derived!L11)) | T11: =IF($D11=1,$Q11,"")
A12: =Derived!A12 | B12: =Derived!B12 | C12: =Derived!C12 | D12: =Derived!K12 | E12: =Derived!F12 | F12: =IF(OR($E12=""),"",MAX(0,MIN(1,(cfg_PBR_max-MIN($E12,cfg_PBR_max))/(cfg_PBR_max-cfg_PBR_floor)))) | G12: =Derived!H12 | H12: =IF(OR($G12=""),"",MAX(0,MIN(1,MIN($G12,cap_NetCashPct)/cap_NetCashPct))) | I12: =Derived!J12 | J12: =IF(OR($I12=""),"",MAX(0,MIN(1,($I12-cfg_Liq_min)/(cfg_Liq_cap-cfg_Liq_min)))) | K12: =Fundamentals!P12 | L12: =Fundamentals!Q12 | M12: =IF(AND($K12="",$L12=""),"",MIN(1,IF($K12="",0,MIN($K12,cap_DivYield)/cap_DivYield)*0.5+IF($L12="",0,MIN($L12,cap_BuybackYield)/cap_BuybackYield)*0.5)) | N12: =IF($A12="","",AVERAGE(IF(Fundamentals!R12="",0,Fundamentals!R12),IF(Fundamentals!S12="",0,Fundamentals!S12),IF(Fundamentals!T12="",0,Fundamentals!T12))) | O12: =IF($A12="","",MAX(0,MIN(1,$N12))) | P12: =IF($A12="","",ROUND(w_PBR*$F12+w_NetCash*$H12+w_Liq*$J12+w_Return*$M12+w_GovAct*$O12,2)) | Q12: =IF($A12="","",$P12+(100000-ROW())/100000000) | R12: =IF($A12="","",IF($D12<>1,"",RANK.EQ($Q12,$Q$3:$Q$202,0))) | S12: =IF($A12="","",IF($D12=1,"",Derived!L12)) | T12: =IF($D12=1,$Q12,"")
A13: =Derived!A13 | B13: =Derived!B13 | C13: =Derived!C13 | D13: =Derived!K13 | E13: =Derived!F13 | F13: =IF(OR($E13=""),"",MAX(0,MIN(1,(cfg_PBR_max-MIN($E13,cfg_PBR_max))/(cfg_PBR_max-cfg_PBR_floor)))) | G13: =Derived!H13 | H13: =IF(OR($G13=""),"",MAX(0,MIN(1,MIN($G13,cap_NetCashPct)/cap_NetCashPct))) | I13: =Derived!J13 | J13: =IF(OR($I13=""),"",MAX(0,MIN(1,($I13-cfg_Liq_min)/(cfg_Liq_cap-cfg_Liq_min)))) | K13: =Fundamentals!P13 | L13: =Fundamentals!Q13 | M13: =IF(AND($K13="",$L13=""),"",MIN(1,IF($K13="",0,MIN($K13,cap_DivYield)/cap_DivYield)*0.5+IF($L13="",0,MIN($L13,cap_BuybackYield)/cap_BuybackYield)*0.5)) | N13: =IF($A13="","",AVERAGE(IF(Fundamentals!R13="",0,Fundamentals!R13),IF(Fundamentals!S13="",0,Fundamentals!S13),IF(Fundamentals!T13="",0,Fundamentals!T13))) | O13: =IF($A13="","",MAX(0,MIN(1,$N13))) | P13: =IF($A13="","",ROUND(w_PBR*$F13+w_NetCash*$H13+w_Liq*$J13+w_Return*$M13+w_GovAct*$O13,2)) | Q13: =IF($A13="","",$P13+(100000-ROW())/100000000) | R13: =IF($A13="","",IF($D13<>1,"",RANK.EQ($Q13,$Q$3:$Q$202,0))) | S13: =IF($A13="","",IF($D13=1,"",Derived!L13)) | T13: =IF($D13=1,$Q13,"")
A14: =Derived!A14 | B14: =Derived!B14 | C14: =Derived!C14 | D14: =Derived!K14 | E14: =Derived!F14 | F14: =IF(OR($E14=""),"",MAX(0,MIN(1,(cfg_PBR_max-MIN($E14,cfg_PBR_max))/(cfg_PBR_max-cfg_PBR_floor)))) | G14: =Derived!H14 | H14: =IF(OR($G14=""),"",MAX(0,MIN(1,MIN($G14,cap_NetCashPct)/cap_NetCashPct))) | I14: =Derived!J14 | J14: =IF(OR($I14=""),"",MAX(0,MIN(1,($I14-cfg_Liq_min)/(cfg_Liq_cap-cfg_Liq_min)))) | K14: =Fundamentals!P14 | L14: =Fundamentals!Q14 | M14: =IF(AND($K14="",$L14=""),"",MIN(1,IF($K14="",0,MIN($K14,cap_DivYield)/cap_DivYield)*0.5+IF($L14="",0,MIN($L14,cap_BuybackYield)/cap_BuybackYield)*0.5)) | N14: =IF($A14="","",AVERAGE(IF(Fundamentals!R14="",0,Fundamentals!R14),IF(Fundamentals!S14="",0,Fundamentals!S14),IF(Fundamentals!T14="",0,Fundamentals!T14))) | O14: =IF($A14="","",MAX(0,MIN(1,$N14))) | P14: =IF($A14="","",ROUND(w_PBR*$F14+w_NetCash*$H14+w_Liq*$J14+w_Return*$M14+w_GovAct*$O14,2)) | Q14: =IF($A14="","",$P14+(100000-ROW())/100000000) | R14: =IF($A14="","",IF($D14<>1,"",RANK.EQ($Q14,$Q$3:$Q$202,0))) | S14: =IF($A14="","",IF($D14=1,"",Derived!L14)) | T14: =IF($D14=1,$Q14,"")
... A202: =Derived!A202 | B202: =Derived!B202 | C202: =Derived!C202 | D202: =Derived!K202 | E202: =Derived!F202 | F202: =IF(OR($E202=""),"",MAX(0,MIN(1,(cfg_PBR_max-MIN($E202,cfg_PBR_max))/(cfg_PBR_max-cfg_PBR_floor)))) | G202: =Derived!H202 | H202: =IF(OR($G202=""),"",MAX(0,MIN(1,MIN($G202,cap_NetCashPct)/cap_NetCashPct))) | I202: =Derived!J202 | J202: =IF(OR($I202=""),"",MAX(0,MIN(1,($I202-cfg_Liq_min)/(cfg_Liq_cap-cfg_Liq_min)))) | K202: =Fundamentals!P202 | L202: =Fundamentals!Q202 | M202: =IF(AND($K202="",$L202=""),"",MIN(1,IF($K202="",0,MIN($K202,cap_DivYield)/cap_DivYield)*0.5+IF($L202="",0,MIN($L202,cap_BuybackYield)/cap_BuybackYield)*0.5)) | N202: =IF($A202="","",AVERAGE(IF(Fundamentals!R202="",0,Fundamentals!R202),IF(Fundamentals!S202="",0,Fundamentals!S202),IF(Fundamentals!T202="",0,Fundamentals!T202))) | O202: =IF($A202="","",MAX(0,MIN(1,$N202))) | P202: =IF($A202="","",ROUND(w_PBR*$F202+w_NetCash*$H202+w_Liq*$J202+w_Return*$M202+w_GovAct*$O202,2)) | Q202: =IF($A202="","",$P202+(100000-ROW())/100000000) | R202: =IF($A202="","",IF($D202<>1,"",RANK.EQ($Q202,$Q$3:$Q$202,0))) | S202: =IF($A202="","",IF($D202=1,"",Derived!L202)) | T202: =IF($D202=1,$Q202,"")

Sheet Report_Top20
A1: Weekly Screening Report — Top 20
A3: Filters & universe notes
A4: Universe | B4: Prime/Standard priority (Growth satellite)
A5: Core filter | B5: PBR<cfg_PBR_max AND NetCash>0 AND Liquidity>=cfg_Liq_min
A6: Sources | B6: Primary sources only; record URLs in Sources sheet
A9: Top 20 (Core-pass only)
A10: Rank | B10: Ticker | C10: Name | D10: Market | E10: PBR | F10: NetCash% | G10: Liquidity (¥mm/day) | H10: Score | I10: PrevRank (input) | J10: Δ Rank | K10: Tag | L10: ScoreKey
A11: 1 | B11: =IF($L11="","",IFERROR(INDEX(Scores!$A$3:$A$202,MATCH($L11,Scores!$T$3:$T$202,0)),"")) | C11: =IF($B11="","",IFERROR(INDEX(Scores!$B$3:$B$202,MATCH($L11,Scores!$T$3:$T$202,0)),"")) | D11: =IF($B11="","",IFERROR(INDEX(Scores!$C$3:$C$202,MATCH($L11,Scores!$T$3:$T$202,0)),"")) | E11: =IF($B11="","",IFERROR(INDEX(Scores!$E$3:$E$202,MATCH($L11,Scores!$T$3:$T$202,0)),"")) | F11: =IF($B11="","",IFERROR(INDEX(Scores!$G$3:$G$202,MATCH($L11,Scores!$T$3:$T$202,0)),"")) | G11: =IF($B11="","",IFERROR(INDEX(Scores!$I$3:$I$202,MATCH($L11,Scores!$T$3:$T$202,0)),"")) | H11: =IF($B11="","",IFERROR(INDEX(Scores!$P$3:$P$202,MATCH($L11,Scores!$T$3:$T$202,0)),"")) | J11: =IF($I11="","",$I11-$A11) | K11: =IF($B11="","",IF($I11="","New",IF($J11>0,"Up",IF($J11<0,"Down","Flat")))) | L11: =IFERROR(LARGE(Scores!$T$3:$T$202,$A11),"")
A12: 2 | B12: =IF($L12="","",IFERROR(INDEX(Scores!$A$3:$A$202,MATCH($L12,Scores!$T$3:$T$202,0)),"")) | C12: =IF($B12="","",IFERROR(INDEX(Scores!$B$3:$B$202,MATCH($L12,Scores!$T$3:$T$202,0)),"")) | D12: =IF($B12="","",IFERROR(INDEX(Scores!$C$3:$C$202,MATCH($L12,Scores!$T$3:$T$202,0)),"")) | E12: =IF($B12="","",IFERROR(INDEX(Scores!$E$3:$E$202,MATCH($L12,Scores!$T$3:$T$202,0)),"")) | F12: =IF($B12="","",IFERROR(INDEX(Scores!$G$3:$G$202,MATCH($L12,Scores!$T$3:$T$202,0)),"")) | G12: =IF($B12="","",IFERROR(INDEX(Scores!$I$3:$I$202,MATCH($L12,Scores!$T$3:$T$202,0)),"")) | H12: =IF($B12="","",IFERROR(INDEX(Scores!$P$3:$P$202,MATCH($L12,Scores!$T$3:$T$202,0)),"")) | J12: =IF($I12="","",$I12-$A12) | K12: =IF($B12="","",IF($I12="","New",IF($J12>0,"Up",IF($J12<0,"Down","Flat")))) | L12: =IFERROR(LARGE(Scores!$T$3:$T$202,$A12),"")
A13: 3 | B13: =IF($L13="","",IFERROR(INDEX(Scores!$A$3:$A$202,MATCH($L13,Scores!$T$3:$T$202,0)),"")) | C13: =IF($B13="","",IFERROR(INDEX(Scores!$B$3:$B$202,MATCH($L13,Scores!$T$3:$T$202,0)),"")) | D13: =IF($B13="","",IFERROR(INDEX(Scores!$C$3:$C$202,MATCH($L13,Scores!$T$3:$T$202,0)),"")) | E13: =IF($B13="","",IFERROR(INDEX(Scores!$E$3:$E$202,MATCH($L13,Scores!$T$3:$T$202,0)),"")) | F13: =IF($B13="","",IFERROR(INDEX(Scores!$G$3:$G$202,MATCH($L13,Scores!$T$3:$T$202,0)),"")) | G13: =IF($B13="","",IFERROR(INDEX(Scores!$I$3:$I$202,MATCH($L13,Scores!$T$3:$T$202,0)),"")) | H13: =IF($B13="","",IFERROR(INDEX(Scores!$P$3:$P$202,MATCH($L13,Scores!$T$3:$T$202,0)),"")) | J13: =IF($I13="","",$I13-$A13) | K13: =IF($B13="","",IF($I13="","New",IF($J13>0,"Up",IF($J13<0,"Down","Flat")))) | L13: =IFERROR(LARGE(Scores!$T$3:$T$202,$A13),"")
A14: 4 | B14: =IF($L14="","",IFERROR(INDEX(Scores!$A$3:$A$202,MATCH($L14,Scores!$T$3:$T$202,0)),"")) | C14: =IF($B14="","",IFERROR(INDEX(Scores!$B$3:$B$202,MATCH($L14,Scores!$T$3:$T$202,0)),"")) | D14: =IF($B14="","",IFERROR(INDEX(Scores!$C$3:$C$202,MATCH($L14,Scores!$T$3:$T$202,0)),"")) | E14: =IF($B14="","",IFERROR(INDEX(Scores!$E$3:$E$202,MATCH($L14,Scores!$T$3:$T$202,0)),"")) | F14: =IF($B14="","",IFERROR(INDEX(Scores!$G$3:$G$202,MATCH($L14,Scores!$T$3:$T$202,0)),"")) | G14: =IF($B14="","",IFERROR(INDEX(Scores!$I$3:$I$202,MATCH($L14,Scores!$T$3:$T$202,0)),"")) | H14: =IF($B14="","",IFERROR(INDEX(Scores!$P$3:$P$202,MATCH($L14,Scores!$T$3:$T$202,0)),"")) | J14: =IF($I14="","",$I14-$A14) | K14: =IF($B14="","",IF($I14="","New",IF($J14>0,"Up",IF($J14<0,"Down","Flat")))) | L14: =IFERROR(LARGE(Scores!$T$3:$T$202,$A14),"")
A15: 5 | B15: =IF($L15="","",IFERROR(INDEX(Scores!$A$3:$A$202,MATCH($L15,Scores!$T$3:$T$202,0)),"")) | C15: =IF($B15="","",IFERROR(INDEX(Scores!$B$3:$B$202,MATCH($L15,Scores!$T$3:$T$202,0)),"")) | D15: =IF($B15="","",IFERROR(INDEX(Scores!$C$3:$C$202,MATCH($L15,Scores!$T$3:$T$202,0)),"")) | E15: =IF($B15="","",IFERROR(INDEX(Scores!$E$3:$E$202,MATCH($L15,Scores!$T$3:$T$202,0)),"")) | F15: =IF($B15="","",IFERROR(INDEX(Scores!$G$3:$G$202,MATCH($L15,Scores!$T$3:$T$202,0)),"")) | G15: =IF($B15="","",IFERROR(INDEX(Scores!$I$3:$I$202,MATCH($L15,Scores!$T$3:$T$202,0)),"")) | H15: =IF($B15="","",IFERROR(INDEX(Scores!$P$3:$P$202,MATCH($L15,Scores!$T$3:$T$202,0)),"")) | J15: =IF($I15="","",$I15-$A15) | K15: =IF($B15="","",IF($I15="","New",IF($J15>0,"Up",IF($J15<0,"Down","Flat")))) | L15: =IFERROR(LARGE(Scores!$T$3:$T$202,$A15),"")
A16: 6 | B16: =IF($L16="","",IFERROR(INDEX(Scores!$A$3:$A$202,MATCH($L16,Scores!$T$3:$T$202,0)),"")) | C16: =IF($B16="","",IFERROR(INDEX(Scores!$B$3:$B$202,MATCH($L16,Scores!$T$3:$T$202,0)),"")) | D16: =IF($B16="","",IFERROR(INDEX(Scores!$C$3:$C$202,MATCH($L16,Scores!$T$3:$T$202,0)),"")) | E16: =IF($B16="","",IFERROR(INDEX(Scores!$E$3:$E$202,MATCH($L16,Scores!$T$3:$T$202,0)),"")) | F16: =IF($B16="","",IFERROR(INDEX(Scores!$G$3:$G$202,MATCH($L16,Scores!$T$3:$T$202,0)),"")) | G16: =IF($B16="","",IFERROR(INDEX(Scores!$I$3:$I$202,MATCH($L16,Scores!$T$3:$T$202,0)),"")) | H16: =IF($B16="","",IFERROR(INDEX(Scores!$P$3:$P$202,MATCH($L16,Scores!$T$3:$T$202,0)),"")) | J16: =IF($I16="","",$I16-$A16) | K16: =IF($B16="","",IF($I16="","New",IF($J16>0,"Up",IF($J16<0,"Down","Flat")))) | L16: =IFERROR(LARGE(Scores!$T$3:$T$202,$A16),"")
A17: 7 | B17: =IF($L17="","",IFERROR(INDEX(Scores!$A$3:$A$202,MATCH($L17,Scores!$T$3:$T$202,0)),"")) | C17: =IF($B17="","",IFERROR(INDEX(Scores!$B$3:$B$202,MATCH($L17,Scores!$T$3:$T$202,0)),"")) | D17: =IF($B17="","",IFERROR(INDEX(Scores!$C$3:$C$202,MATCH($L17,Scores!$T$3:$T$202,0)),"")) | E17: =IF($B17="","",IFERROR(INDEX(Scores!$E$3:$E$202,MATCH($L17,Scores!$T$3:$T$202,0)),"")) | F17: =IF($B17="","",IFERROR(INDEX(Scores!$G$3:$G$202,MATCH($L17,Scores!$T$3:$T$202,0)),"")) | G17: =IF($B17="","",IFERROR(INDEX(Scores!$I$3:$I$202,MATCH($L17,Scores!$T$3:$T$202,0)),"")) | H17: =IF($B17="","",IFERROR(INDEX(Scores!$P$3:$P$202,MATCH($L17,Scores!$T$3:$T$202,0)),"")) | J17: =IF($I17="","",$I17-$A17) | K17: =IF($B17="","",IF($I17="","New",IF($J17>0,"Up",IF($J17<0,"Down","Flat")))) | L17: =IFERROR(LARGE(Scores!$T$3:$T$202,$A17),"")
A18: 8 | B18: =IF($L18="","",IFERROR(INDEX(Scores!$A$3:$A$202,MATCH($L18,Scores!$T$3:$T$202,0)),"")) | C18: =IF($B18="","",IFERROR(INDEX(Scores!$B$3:$B$202,MATCH($L18,Scores!$T$3:$T$202,0)),"")) | D18: =IF($B18="","",IFERROR(INDEX(Scores!$C$3:$C$202,MATCH($L18,Scores!$T$3:$T$202,0)),"")) | E18: =IF($B18="","",IFERROR(INDEX(Scores!$E$3:$E$202,MATCH($L18,Scores!$T$3:$T$202,0)),"")) | F18: =IF($B18="","",IFERROR(INDEX(Scores!$G$3:$G$202,MATCH($L18,Scores!$T$3:$T$202,0)),"")) | G18: =IF($B18="","",IFERROR(INDEX(Scores!$I$3:$I$202,MATCH($L18,Scores!$T$3:$T$202,0)),"")) | H18: =IF($B18="","",IFERROR(INDEX(Scores!$P$3:$P$202,MATCH($L18,Scores!$T$3:$T$202,0)),"")) | J18: =IF($I18="","",$I18-$A18) | K18: =IF($B18="","",IF($I18="","New",IF($J18>0,"Up",IF($J18<0,"Down","Flat")))) | L18: =IFERROR(LARGE(Scores!$T$3:$T$202,$A18),"")
A19: 9 | B19: =IF($L19="","",IFERROR(INDEX(Scores!$A$3:$A$202,MATCH($L19,Scores!$T$3:$T$202,0)),"")) | C19: =IF($B19="","",IFERROR(INDEX(Scores!$B$3:$B$202,MATCH($L19,Scores!$T$3:$T$202,0)),"")) | D19: =IF($B19="","",IFERROR(INDEX(Scores!$C$3:$C$202,MATCH($L19,Scores!$T$3:$T$202,0)),"")) | E19: =IF($B19="","",IFERROR(INDEX(Scores!$E$3:$E$202,MATCH($L19,Scores!$T$3:$T$202,0)),"")) | F19: =IF($B19="","",IFERROR(INDEX(Scores!$G$3:$G$202,MATCH($L19,Scores!$T$3:$T$202,0)),"")) | G19: =IF($B19="","",IFERROR(INDEX(Scores!$I$3:$I$202,MATCH($L19,Scores!$T$3:$T$202,0)),"")) | H19: =IF($B19="","",IFERROR(INDEX(Scores!$P$3:$P$202,MATCH($L19,Scores!$T$3:$T$202,0)),"")) | J19: =IF($I19="","",$I19-$A19) | K19: =IF($B19="","",IF($I19="","New",IF($J19>0,"Up",IF($J19<0,"Down","Flat")))) | L19: =IFERROR(LARGE(Scores!$T$3:$T$202,$A19),"")
A20: 10 | B20: =IF($L20="","",IFERROR(INDEX(Scores!$A$3:$A$202,MATCH($L20,Scores!$T$3:$T$202,0)),"")) | C20: =IF($B20="","",IFERROR(INDEX(Scores!$B$3:$B$202,MATCH($L20,Scores!$T$3:$T$202,0)),"")) | D20: =IF($B20="","",IFERROR(INDEX(Scores!$C$3:$C$202,MATCH($L20,Scores!$T$3:$T$202,0)),"")) | E20: =IF($B20="","",IFERROR(INDEX(Scores!$E$3:$E$202,MATCH($L20,Scores!$T$3:$T$202,0)),"")) | F20: =IF($B20="","",IFERROR(INDEX(Scores!$G$3:$G$202,MATCH($L20,Scores!$T$3:$T$202,0)),"")) | G20: =IF($B20="","",IFERROR(INDEX(Scores!$I$3:$I$202,MATCH($L20,Scores!$T$3:$T$202,0)),"")) | H20: =IF($B20="","",IFERROR(INDEX(Scores!$P$3:$P$202,MATCH($L20,Scores!$T$3:$T$202,0)),"")) | J20: =IF($I20="","",$I20-$A20) | K20: =IF($B20="","",IF($I20="","New",IF($J20>0,"Up",IF($J20<0,"Down","Flat")))) | L20: =IFERROR(LARGE(Scores!$T$3:$T$202,$A20),"")
A21: 11 | B21: =IF($L21="","",IFERROR(INDEX(Scores!$A$3:$A$202,MATCH($L21,Scores!$T$3:$T$202,0)),"")) | C21: =IF($B21="","",IFERROR(INDEX(Scores!$B$3:$B$202,MATCH($L21,Scores!$T$3:$T$202,0)),"")) | D21: =IF($B21="","",IFERROR(INDEX(Scores!$C$3:$C$202,MATCH($L21,Scores!$T$3:$T$202,0)),"")) | E21: =IF($B21="","",IFERROR(INDEX(Scores!$E$3:$E$202,MATCH($L21,Scores!$T$3:$T$202,0)),"")) | F21: =IF($B21="","",IFERROR(INDEX(Scores!$G$3:$G$202,MATCH($L21,Scores!$T$3:$T$202,0)),"")) | G21: =IF($B21="","",IFERROR(INDEX(Scores!$I$3:$I$202,MATCH($L21,Scores!$T$3:$T$202,0)),"")) | H21: =IF($B21="","",IFERROR(INDEX(Scores!$P$3:$P$202,MATCH($L21,Scores!$T$3:$T$202,0)),"")) | J21: =IF($I21="","",$I21-$A21) | K21: =IF($B21="","",IF($I21="","New",IF($J21>0,"Up",IF($J21<0,"Down","Flat")))) | L21: =IFERROR(LARGE(Scores!$T$3:$T$202,$A21),"")
A22: 12 | B22: =IF($L22="","",IFERROR(INDEX(Scores!$A$3:$A$202,MATCH($L22,Scores!$T$3:$T$202,0)),"")) | C22: =IF($B22="","",IFERROR(INDEX(Scores!$B$3:$B$202,MATCH($L22,Scores!$T$3:$T$202,0)),"")) | D22: =IF($B22="","",IFERROR(INDEX(Scores!$C$3:$C$202,MATCH($L22,Scores!$T$3:$T$202,0)),"")) | E22: =IF($B22="","",IFERROR(INDEX(Scores!$E$3:$E$202,MATCH($L22,Scores!$T$3:$T$202,0)),"")) | F22: =IF($B22="","",IFERROR(INDEX(Scores!$G$3:$G$202,MATCH($L22,Scores!$T$3:$T$202,0)),"")) | G22: =IF($B22="","",IFERROR(INDEX(Scores!$I$3:$I$202,MATCH($L22,Scores!$T$3:$T$202,0)),"")) | H22: =IF($B22="","",IFERROR(INDEX(Scores!$P$3:$P$202,MATCH($L22,Scores!$T$3:$T$202,0)),"")) | J22: =IF($I22="","",$I22-$A22) | K22: =IF($B22="","",IF($I22="","New",IF($J22>0,"Up",IF($J22<0,"Down","Flat")))) | L22: =IFERROR(LARGE(Scores!$T$3:$T$202,$A22),"")
... A30: 20 | B30: =IF($L30="","",IFERROR(INDEX(Scores!$A$3:$A$202,MATCH($L30,Scores!$T$3:$T$202,0)),"")) | C30: =IF($B30="","",IFERROR(INDEX(Scores!$B$3:$B$202,MATCH($L30,Scores!$T$3:$T$202,0)),"")) | D30: =IF($B30="","",IFERROR(INDEX(Scores!$C$3:$C$202,MATCH($L30,Scores!$T$3:$T$202,0)),"")) | E30: =IF($B30="","",IFERROR(INDEX(Scores!$E$3:$E$202,MATCH($L30,Scores!$T$3:$T$202,0)),"")) | F30: =IF($B30="","",IFERROR(INDEX(Scores!$G$3:$G$202,MATCH($L30,Scores!$T$3:$T$202,0)),"")) | G30: =IF($B30="","",IFERROR(INDEX(Scores!$I$3:$I$202,MATCH($L30,Scores!$T$3:$T$202,0)),"")) | H30: =IF($B30="","",IFERROR(INDEX(Scores!$P$3:$P$202,MATCH($L30,Scores!$T$3:$T$202,0)),"")) | J30: =IF($I30="","",$I30-$A30) | K30: =IF($B30="","",IF($I30="","New",IF($J30>0,"Up",IF($J30<0,"Down","Flat")))) | L30: =IFERROR(LARGE(Scores!$T$3:$T$202,$A30),"")

Sheet QC
A1: QC Dashboard
A3: Checks
A4: Tickers populated (Fundamentals) | B4: =COUNTA(Fundamentals!$A$3:$A$202)
A5: Core-pass count | B5: =COUNTIF(Derived!$K$3:$K$202,1)
A6: Missing critical data (flag) | B6: =COUNTIF(Derived!$M$3:$M$202,1)
A7: Missing financials URL (where ticker exists) | B7: =COUNTIFS(Fundamentals!$A$3:$A$202,"<>",Fundamentals!$V$3:$V$202,"")
A8: Missing EDINET URL (where ticker exists) | B8: =COUNTIFS(Fundamentals!$A$3:$A$202,"<>",Fundamentals!$W$3:$W$202,"")
A9: Missing capital policy URL (where ticker exists) | B9: =COUNTIFS(Fundamentals!$A$3:$A$202,"<>",Fundamentals!$X$3:$X$202,"")
A12: Notes
A13: If Missing critical data > 0, complete blue inputs or record N/A explicitly with notes + primary URL.

Sheet Sources
A1: Sources (Primary source log — TDnet/JPX/EDINET/Issuer IR PDFs only)
A2: Ticker | B2: Field | C2: Value | D2: Unit | E2: Period | F2: Primary Source URL | G2: Publication Date (JST) | H2: Notes
